{
  "version": 1,
  "visualMode": "cosmic-wormhole",
  "visualTuning": {
    "audioSensitivity": 1.1,
    "backgroundRed": 4,
    "backgroundGreen": 3,
    "backgroundBlue": 14,
    "circleHue": 45,
    "lineAlpha": 1.55,
    "lineWeight": 1.1,
    "wormholeRadius": 1.5,
    "wormholeDepth": 4.6,
    "wormholeSpeed": 0.75,
    "wormholeWarp": 0.35,
    "wormholeCurve": 0.12,
    "wormholePathBend": 0.22,
    "wormholePathBendVertical": 0.12,
    "wormholeRing": 0,
    "wormholeDepthCoherence": 0,
    "wormholeContinuity": 2.0,
    "wormholeEmissionMode": 0,
    "wormholeJitter": 0
  }
}
